README.md
setup.cfg
setup.py
tests/__init__.py
tests/test_vizard.py
tests/test_vizardin.py
vizard/Viz2PDF.py
vizard/Vizard.py
vizard/VizardIn.py
vizard/__init__.py
vizard.egg-info/PKG-INFO
vizard.egg-info/SOURCES.txt
vizard.egg-info/dependency_links.txt
vizard.egg-info/requires.txt
vizard.egg-info/top_level.txt