Metadata-Version: 2.1
Name: vizard
Version: 1.3.0
Summary: Intuitive, Interactive, Easy and Quick Visualizations for Data Science Projects
Home-page: https://github.com/Ritvik19
Author: Ritvik Rastogi
Author-email: rastogiritvik99@gmail.com
License: UNKNOWN
Platform: UNKNOWN
Classifier: Programming Language :: Python :: 3
Classifier: License :: OSI Approved :: MIT License
Classifier: Operating System :: OS Independent
